[
	{
		"img": "Images/stars.png",
		"title": "Extra Night Show",
		"day": "",
		"provider": "Antena Stars",
		"date": "17.03.2017"
	},
	{
		"img": "Images/stars.png",
		"title": "Extra Night Show",
		"day": "",
		"provider": "Antena Stars",
		"date": "11.02.2017"
	},
	{
		"img": "Images/stars.png",
		"title": "Extra Night Show",
		"day": "",
		"provider": "Antena Stars",
		"date": "9.02.2017"
	},
	{
		"img": "Images/stars.png",
		"title": "Extra Night Show",
		"day": "",
		"provider": "Antena Stars",
		"date": "6.02.2017"
	},
	{
		"img": "Images/stars.png",
		"title": "Extra Night Show",
		"day": "",
		"provider": "Antena Stars",
		"date": "16.03.2017"
	},
	{
		"img": "Images/stars.png",
		"title": "Extra Night Show",
		"day": "",
		"provider": "Antena Stars",
		"date": "10.03.2017"
	},
	{
		"img": "Images/stars.pngg",
		"title": "Extra Night Show",
		"day": "",
		"provider": "Antena Stars",
		"date": "11.03.2017"
	},
	{
		"img": "Images/stars.png",
		"title": "Extra Night Show",
		"day": "",
		"provider": "Antena Stars",
		"date": "16.04.2017"
	},
	{
		"img": "Images/stars.pngg",
		"title": "Extra Night Show",
		"day": "",
		"provider": "Antena Stars",
		"date": "16.04.2017"
	},
	{
		"img": "Images/stars.png",
		"title": "Extra Night Show",
		"day": "7",		
		"provider": "Antena Stars",
		"date": "7.04.2017"
	},
	{
		"img": "Images/stars.png",
		"title": "Extra Night Show",
		"day": "",
		"provider": "Antena Stars",
		"date": "16.04.2017"
	}
]
